unittest_benchmark.py
unittest_benchmark-0.1.2.dist-info/licenses/LICENSE
unittest_benchmark-0.1.2.dist-info/METADATA
unittest_benchmark-0.1.2.dist-info/WHEEL
unittest_benchmark-0.1.2.dist-info/top_level.txt
unittest_benchmark-0.1.2.dist-info/RECORD
