Metadata-Version: 2.4
Name: unittest-benchmark
Version: 0.1.2
Requires-Python: >=3.12
License-File: LICENSE
Requires-Dist: scipy>=1.15
Dynamic: license-file
